Metadata-Version: 2.1
Name: pylogix-001
Version: 3.9.21
Summary: Pylogix is a leading custom software development company that provides innovative solutions to businesses worldwide. Our experienced team of developers specializes in creating custom software that is easy to use, visually appealing, and tailored to our clients' specific needs. Visit us at https://pylogix.com/ to learn more about our custom software development services.
Home-page: https://github.com/PYLOGiX-DEV/PYLOGiX-DEV
Author: https://pylogix.com/
Author-email: dev@pylogix.com
License: MIT License
Classifier: Programming Language :: Python :: 3
Classifier: License :: OSI Approved :: MIT License
Classifier: Operating System :: OS Independent
Requires-Python: >=3.6
License-File: license.txt
